materialized_intelligence/__init__.py
materialized_intelligence/cli.py
materialized_intelligence/sdk.py
materialized_intelligence-0.1.11.dist-info/METADATA
materialized_intelligence-0.1.11.dist-info/WHEEL
materialized_intelligence-0.1.11.dist-info/entry_points.txt
materialized_intelligence-0.1.11.dist-info/licenses/LICENSE
materialized_intelligence-0.1.11.dist-info/RECORD
