Metadata-Version: 2.4
Name: materialized-intelligence
Version: 0.1.11
Summary: Materialized Intelligence SDK
Project-URL: Homepage, https://materialized.dev
Project-URL: Documentation, https://docs.materialized.dev
License-Expression: Apache-2.0
License-File: LICENSE
Requires-Python: >=3.10
Requires-Dist: click==8.1.7
Requires-Dist: colorama==0.4.4
Requires-Dist: numpy==2.1.1
Requires-Dist: pandas==2.2.3
Requires-Dist: polars==1.8.2
Requires-Dist: pydantic==2.11.4
Requires-Dist: requests==2.32.3
Requires-Dist: tqdm==4.67.1
Requires-Dist: yaspin==3.1.0
